tablpy/__init__.py
tablpy/extra_funcs.py
tablpy/table.py
tablpy/units.py
tablpy-0.15.5.dist-info/WHEEL
tablpy-0.15.5.dist-info/METADATA
tablpy-0.15.5.dist-info/RECORD
