Metadata-Version: 2.1
Name: tablpy
Version: 0.15.5
Summary: A package that makes importing and handeling data
Home-page: https://github.com/AmdaUwU/tablpy
License: MIT
Author: AmdaUwU
Author-email: jbat2000@gmail.com
Requires-Python: >=3.8,<4.0
Classifier: License :: OSI Approved :: MIT License
Classifier: Programming Language :: Python :: 3
Classifier: Programming Language :: Python :: 3.10
Classifier: Programming Language :: Python :: 3.8
Classifier: Programming Language :: Python :: 3.9
Requires-Dist: matplotlib (>=3.3.4,<4.0.0)
Requires-Dist: pandas (>=1.2.2,<2.0.0)
Requires-Dist: scipy (>=1.6.0,<2.0.0)
Requires-Dist: sympy (>=1.7.1,<2.0.0)
